{
    "macros": [
        {
            "file": "1766664109_821dc7.macro",
            "name": [
                "",
                "",
                ""
            ],
            "desc": [
                "",
                "",
                ""
            ],
            "author": "",
            "status": "draft",
            "expire": 1766665909
        },
        {
            "file": "1766664111_0139d6.macro",
            "name": [
                "",
                "",
                ""
            ],
            "desc": [
                "",
                "",
                ""
            ],
            "author": "",
            "status": "draft",
            "expire": 1766665911
        },
        {
            "file": "1766664112_cf2de6.macro",
            "name": [
                "",
                "",
                ""
            ],
            "desc": [
                "",
                "",
                ""
            ],
            "author": "",
            "status": "draft",
            "expire": 1766665912
        }
    ]
}