{
    "macros": [
        {
            "file": "1766493627_0b7d83.macro",
            "name": [
                "",
                "",
                ""
            ],
            "desc": [
                "",
                "",
                ""
            ],
            "author": "",
            "status": "draft",
            "expire": 1766495427
        },
        {
            "file": "1766493644_c19d5c.macro",
            "name": [
                "",
                "",
                ""
            ],
            "desc": [
                "",
                "",
                ""
            ],
            "author": "",
            "status": "draft",
            "expire": 1766495444
        },
        {
            "file": "1766493647_99ed1a.macro",
            "name": [
                "",
                "",
                ""
            ],
            "desc": [
                "",
                "",
                ""
            ],
            "author": "",
            "status": "draft",
            "expire": 1766495447
        },
        {
            "file": "1766493650_e45401.macro",
            "name": [
                "",
                "",
                ""
            ],
            "desc": [
                "",
                "",
                ""
            ],
            "author": "",
            "status": "draft",
            "expire": 1766495450
        }
    ]
}